[{"id":"1","nombre":"Sitio Turístico 1","resumen":"Descripción del Sitio Turístico 1","latitud":123.456,"longitud":789.012,"urlArticulo":"https://ejemplo.com/articulo1","categorias":["\"\\\"\\\\\\\"Naturaleza\\\\\\\"\\\"\"","\"\\\"\\\\\\\"Historia\\\\\\\"\\\"\""],"enlaces":["\"\\\"\\\\\\\"https://ejemplo.com/enlace1\\\\\\\"\\\"\"","\"\\\"\\\\\\\"https://ejemplo.com/enlace2\\\\\\\"\\\"\""]},{"id":"2","nombre":"Sitio Turístico 2","resumen":"Descripción del Sitio Turístico 2","latitud":456.789,"longitud":123.012,"urlArticulo":"https://ejemplo.com/articulo2","categorias":["\"\\\"\\\\\\\"Cultura\\\\\\\"\\\"\"","\"\\\"\\\\\\\"Aventura\\\\\\\"\\\"\""],"enlaces":["\"\\\"\\\\\\\"https://ejemplo.com/enlace3\\\\\\\"\\\"\"","\"\\\"\\\\\\\"https://ejemplo.com/enlace4\\\\\\\"\\\"\""]},{"id":"0434421d-528f-4125-825d-f6df7a288970","nombre":"1","resumen":"Ejemplooooo","latitud":40.0,"longitud":-74.0,"urlArticulo":"https://ejemplo.com","categorias":["\"\\\"\\\\\\\"Naturaleza\\\\\\\"\\\"\"","\"\\\"\\\\\\\"Cultura\\\\\\\"\\\"\""],"enlaces":["\"\\\"\\\\\\\"https://enlace1.com\\\\\\\"\\\"\"","\"\\\"\\\\\\\"https://enlace2.com\\\\\\\"\\\"\""]},{"id":"d2c0c614-5e4e-4f34-81af-6f9cfa48f570","nombre":"1","resumen":"Ejemplooooo","latitud":40.0,"longitud":-74.0,"urlArticulo":"https://ejemplo.com","categorias":["\"\\\"Naturaleza\\\"\"","\"\\\"Cultura\\\"\""],"enlaces":["\"\\\"https://enlace1.com\\\"\"","\"\\\"https://enlace2.com\\\"\""]},{"id":"38d11743-fca8-4144-801e-510a103a7bd5","nombre":"1","resumen":"Ejemplooooo","latitud":40.0,"longitud":-74.0,"urlArticulo":"https://ejemplo.com","categorias":["\"Naturaleza\"","\"Cultura\""],"enlaces":["\"https://enlace1.com\"","\"https://enlace2.com\""]},{"id":"a41257ad-fd62-4c0b-90cb-2beab5bf0b0c","nombre":"1","resumen":"Ejemplooooo","latitud":40.0,"longitud":-74.0,"urlArticulo":"https://ejemplo.com","categorias":["Naturaleza","Cultura"],"enlaces":["https://enlace1.com","https://enlace2.com"]}]